genalyzer/__init__.py
genalyzer/pygenalyzer.py
genalyzer/helpers/__init__.py
genalyzer/helpers/waveform_gen.py
genalyzer/simplified_beta/__init__.py
genalyzer/simplified_beta/simplified_beta.py
genalyzer-0.1.1.dist-info/METADATA
genalyzer-0.1.1.dist-info/WHEEL
genalyzer-0.1.1.dist-info/top_level.txt
genalyzer-0.1.1.dist-info/RECORD
