Metadata-Version: 2.1
Name: genalyzer
Version: 0.1.1
Summary: Python bindings for genalyzer converter analysis library
Author-email: Peter Derounian <peter.derounian@analog.com>, Srikanth Pagadarai <srikanth.pagadarai@analog.com>, Travis Collins <travis.collins@analog.com>
Maintainer: Analog Devices, Inc
Maintainer-email: Srikanth Pagadarai <srikanth.pagadarai@analog.com>, Travis Collins <travis.collins@analog.com>
License: ADI BSD
Project-URL: homepage, https://analogdevicesinc.github.io/genalyzer/
Project-URL: documentation, https://analogdevicesinc.github.io/genalyzer/
Project-URL: repository, https://github.com/analogdevicesinc/genalyzer
Classifier: Intended Audience :: Developers
Classifier: Operating System :: OS Independent
Classifier: Programming Language :: Python :: 3
Classifier: Programming Language :: Python :: 3.7
Classifier: Programming Language :: Python :: 3.8
Classifier: Programming Language :: Python :: 3.9
Classifier: Programming Language :: Python :: 3.10
Classifier: Programming Language :: Python :: 3.11
Classifier: Topic :: Software Development :: Libraries :: Python Modules
Requires-Python: >=3.7
Requires-Dist: numpy >=1.20
Provides-Extra: tools
Requires-Dist: scipy ; extra == 'tools'
